[
    {
        "storyTitle": "{tables}",
        "storyHref": "https://www.forexfactory.com/news/1288907-jpn-business-outlook-survey-april-june-2024",
        "redirectUrl": "https://www.forexfactory.com/news/1288907-jpn-business-outlook-survey-april-june-2024/hit",
        "timeText": "9 min ago",
        "when": "2024-06-13T00:00:07.756Z",
        "whenNumber": 1718236807756,
        "storyClassList": "flexposts__item flexposts__story flexposts__story--low story low"
    },
    {
        "storyTitle": "Markets took back about half of this morning’s post-CPI rally (recap here) as the full set of FOMC communications worked through. Some of...",
        "storyHref": "https://www.forexfactory.com/news/1288904-median-versus-mode-on-the-fomc",
        "redirectUrl": "https://www.forexfactory.com/news/1288904-median-versus-mode-on-the-fomc/hit",
        "timeText": "14 min ago",
        "when": "2024-06-13T00:00:07.756Z",
        "whenNumber": 1718236807756,
        "storyClassList": "flexposts__item flexposts__story flexposts__story--none story "
    },
    {
        "storyTitle": "Mexico could intervene to restore order if currency market volatility ever becomes “extreme,” central bank Governor Victoria Rodriguez ...",
        "storyHref": "https://www.forexfactory.com/news/1288901-banxico-says-it-can-step-in-if-peso",
        "redirectUrl": "https://www.forexfactory.com/news/1288901-banxico-says-it-can-step-in-if-peso/hit",
        "timeText": "1 hr ago",
        "when": "2024-06-13T00:00:07.756Z",
        "whenNumber": 1718236807756,
        "storyClassList": "flexposts__item flexposts__story flexposts__story--none story "
    },
    {
        "storyTitle": "GBP/JPY found a new 16-year high of 200.95 on Wednesday, with Guppy bidders shrugging off a steep miss in UK manufacturing activity as the...",
        "storyHref": "https://www.forexfactory.com/news/1288899-gbpjpy-shrugs-off-uk-data-misses-to-test",
        "redirectUrl": "https://www.forexfactory.com/news/1288899-gbpjpy-shrugs-off-uk-data-misses-to-test/hit",
        "timeText": "1 hr 37 min ago",
        "when": "2024-06-13T00:00:07.756Z",
        "whenNumber": 1718236807756,
        "storyClassList": "flexposts__item flexposts__story flexposts__story--none story "
    },
    {
        "storyTitle": "The euro zone’s underlying consumer price growth is proving stubborn, according to European Central Bank Governing Council member Joachim...",
        "storyHref": "https://www.forexfactory.com/news/1288893-ecbs-nagel-says-euro-zone-core-inflation-is-still",
        "redirectUrl": "https://www.forexfactory.com/news/1288893-ecbs-nagel-says-euro-zone-core-inflation-is-still/hit",
        "timeText": "2 hr 19 min ago",
        "when": "2024-06-13T00:00:07.756Z",
        "whenNumber": 1718236807756,
        "storyClassList": "flexposts__item flexposts__story flexposts__story--none story "
    },
    {
        "storyTitle": "Euro futures traded higher, German inflation was unrevised, U.S. CPI softer than expected, Bob Iaccino has more.",
        "storyHref": "https://www.forexfactory.com/news/1288889-euro-futures-traded-higher-german-inflation-was-unrevised",
        "redirectUrl": "https://www.forexfactory.com/news/1288889-euro-futures-traded-higher-german-inflation-was-unrevised/hit",
        "timeText": "2 hr 59 min ago",
        "when": "2024-06-13T00:00:07.756Z",
        "whenNumber": 1718236807756,
        "storyClassList": "flexposts__item flexposts__story flexposts__story--none story "
    },
    {
        "storyTitle": "The dollar dropped on Wednesday after data showed that consumer prices in May rose less than economists expected, but pared losses after ...",
        "storyHref": "https://www.forexfactory.com/news/1288887-dollar-pares-losses-as-fed-officials-project-only",
        "redirectUrl": "https://www.forexfactory.com/news/1288887-dollar-pares-losses-as-fed-officials-project-only/hit",
        "timeText": "3 hr ago",
        "when": "2024-06-13T00:00:07.756Z",
        "whenNumber": 1718236807756,
        "storyClassList": "flexposts__item flexposts__story flexposts__story--none story "
    },
    {
        "storyTitle": "The Federal Reserve on Wednesday kept its key interest rate unchanged and signaled that just one cut is expected before the end of the ...",
        "storyHref": "https://www.forexfactory.com/news/1288885-fed-holds-rates-steady-indicates-only-one-cut",
        "redirectUrl": "https://www.forexfactory.com/news/1288885-fed-holds-rates-steady-indicates-only-one-cut/hit",
        "timeText": "4 hr ago",
        "when": "2024-06-13T00:00:07.756Z",
        "whenNumber": 1718236807756,
        "storyClassList": "flexposts__item flexposts__story flexposts__story--none story "
    },
    {
        "storyTitle": "post: BoC’s Macklem: MonPol No Longer Needs To Be As Restrictive As It Has Been - Still Need To Get Inflation Down Further To Our Targets...",
        "storyHref": "https://www.forexfactory.com/news/1288883-bocs-macklem-monpol-no-longer-needs-to-be",
        "redirectUrl": "https://www.forexfactory.com/news/1288883-bocs-macklem-monpol-no-longer-needs-to-be/hit",
        "timeText": "4 hr ago",
        "when": "2024-06-13T00:00:07.756Z",
        "whenNumber": 1718236807756,
        "storyClassList": "flexposts__item flexposts__story flexposts__story--low story low"
    },
    {
        "storyTitle": "post: MORE FED'S POWELL Q&A: IN HOUSING, FOUND THERE ARE 'BIT LAGS' IN DATA THAT MAY TAKE 'SEVERAL YEARS' BEFORE IMPROVEMENTS SHOW UP...",
        "storyHref": "https://www.forexfactory.com/news/1288882-feds-powell-in-housing-there-are-big-lags",
        "redirectUrl": "https://www.forexfactory.com/news/1288882-feds-powell-in-housing-there-are-big-lags/hit",
        "timeText": "4 hr ago",
        "when": "2024-06-13T00:00:07.757Z",
        "whenNumber": 1718236807757,
        "storyClassList": "flexposts__item flexposts__story flexposts__story--high story high"
    }
]